.DS_Store
om2m_client/__init__.py
om2m_client/client.py
om2m_client/exceptions.py
om2m_client/test.py
micropython_om2m_client-0.1.0a7.dist-info/LICENSE
micropython_om2m_client-0.1.0a7.dist-info/METADATA
micropython_om2m_client-0.1.0a7.dist-info/WHEEL
micropython_om2m_client-0.1.0a7.dist-info/top_level.txt
micropython_om2m_client-0.1.0a7.dist-info/RECORD
