Metadata-Version: 2.1
Name: micropython-om2m-client
Version: 0.1.0a7
Summary: A MicroPython client for interacting with OM2M CSE (Work in Progress).
Home-page: https://github.com/SCRCE/micropython-om2m-client
Author: Ahmad Hammad
Author-email: ahmadhammad.uca@gmail.com
Classifier: Development Status :: 2 - Pre-Alpha
Classifier: Intended Audience :: Developers
Classifier: Programming Language :: Python :: Implementation :: MicroPython
License-File: LICENSE
Requires-Dist: urequests >=0.9.0
Requires-Dist: ujson >=1.35
Requires-Dist: umqtt.robust >=1.0.0
